pytest_allure_collection/__init__.py
pytest_allure_collection/__version__.py
pytest_allure_collection-0.0.5.dist-info/LICENSE
pytest_allure_collection-0.0.5.dist-info/METADATA
pytest_allure_collection-0.0.5.dist-info/WHEEL
pytest_allure_collection-0.0.5.dist-info/entry_points.txt
pytest_allure_collection-0.0.5.dist-info/top_level.txt
pytest_allure_collection-0.0.5.dist-info/RECORD
